[{"line":2,"elements":[{"line":3,"name":"","description":"","type":"background","keyword":"Background","steps":[{"result":{"status":"undefined"},"line":4,"name":"the user is on https://techglobal-training.com/frontend/project-5","match":{},"keyword":"Given "}]},{"start_timestamp":"2023-07-04T05:19:15.873Z","before":[{"result":{"duration":3204000000,"status":"passed"},"match":{"location":"steps.BaseSteps.setup()"}},{"result":{"duration":9000000,"status":"passed"},"match":{"location":"steps.EtsySteps.setDriver()"}},{"result":{"duration":4000000,"status":"passed"},"match":{"location":"steps.GoogleSteps.setDriver()"}},{"result":{"duration":4000000,"status":"passed"},"match":{"location":"steps.TechGlobalProject4Steps.setDriver()"}},{"result":{"duration":3000000,"status":"passed"},"match":{"location":"steps.TechGlobalSteps.setDriver()"}},{"result":{"duration":1000000,"status":"passed"},"match":{"location":"steps.WikiSteps.setDriver()"}}],"line":6,"name":"","description":"","id":"pagination-validation;","after":[{"result":{"duration":610000000,"status":"passed"},"match":{"location":"steps.Hooks.tearDown(io.cucumber.java.Scenario)"}}],"type":"scenario","keyword":"Scenario","steps":[{"result":{"status":"skipped"},"line":7,"name":"the user should see the “Pagination” heading","match":{},"keyword":"Then "},{"result":{"status":"skipped"},"line":8,"name":"the user should see the “World City Populations 2022” heading","match":{},"keyword":"And "},{"result":{"status":"skipped"},"line":9,"name":"the user should see the “What are the most populated cities in the world? Here is a list of the top five most populated cities in the world:” paragraph","match":{},"keyword":"And "}],"tags":[{"name":"@Project5"}]},{"line":3,"name":"","description":"","type":"background","keyword":"Background","steps":[{"result":{"status":"undefined"},"line":4,"name":"the user is on https://techglobal-training.com/frontend/project-5","match":{},"keyword":"Given "}]},{"start_timestamp":"2023-07-04T05:19:19.779Z","before":[{"result":{"duration":1111000000,"status":"passed"},"match":{"location":"steps.BaseSteps.setup()"}},{"result":{"status":"passed"},"match":{"location":"steps.EtsySteps.setDriver()"}},{"result":{"status":"passed"},"match":{"location":"steps.GoogleSteps.setDriver()"}},{"result":{"duration":2000000,"status":"passed"},"match":{"location":"steps.TechGlobalProject4Steps.setDriver()"}},{"result":{"status":"passed"},"match":{"location":"steps.TechGlobalSteps.setDriver()"}},{"result":{"status":"passed"},"match":{"location":"steps.WikiSteps.setDriver()"}}],"line":11,"name":"","description":"","id":"pagination-validation;","after":[{"result":{"duration":602000000,"status":"passed"},"match":{"location":"steps.Hooks.tearDown(io.cucumber.java.Scenario)"}}],"type":"scenario","keyword":"Scenario","steps":[{"result":{"status":"skipped"},"line":12,"name":"the user should see the “Previous” button is disabled","match":{},"keyword":"Then "},{"result":{"status":"skipped"},"line":13,"name":"the user should see the “Next” button is enabled","match":{},"keyword":"And "},{"result":{"status":"skipped"},"line":14,"name":"the user clicks on the “Next” button","match":{},"keyword":"When "},{"result":{"status":"skipped"},"line":15,"name":"the user should see the “Previous” button is enabled","match":{},"keyword":"Then "},{"result":{"status":"skipped"},"line":16,"name":"the user clicks on the “Next” button till it becomes disabled","match":{},"keyword":"When "},{"result":{"status":"skipped"},"line":17,"name":"the user should see the “Previous” button is enabled","match":{},"keyword":"Then "},{"result":{"status":"skipped"},"line":18,"name":"the user should see the “Next” button is disabled","match":{},"keyword":"And "}],"tags":[{"name":"@Project5"}]},{"line":3,"name":"","description":"","type":"background","keyword":"Background","steps":[{"result":{"status":"undefined"},"line":4,"name":"the user is on https://techglobal-training.com/frontend/project-5","match":{},"keyword":"Given "}]},{"start_timestamp":"2023-07-04T05:19:21.504Z","before":[{"result":{"duration":1136000000,"status":"passed"},"match":{"location":"steps.BaseSteps.setup()"}},{"result":{"status":"passed"},"match":{"location":"steps.EtsySteps.setDriver()"}},{"result":{"status":"passed"},"match":{"location":"steps.GoogleSteps.setDriver()"}},{"result":{"status":"passed"},"match":{"location":"steps.TechGlobalProject4Steps.setDriver()"}},{"result":{"status":"passed"},"match":{"location":"steps.TechGlobalSteps.setDriver()"}},{"result":{"duration":2000000,"status":"passed"},"match":{"location":"steps.WikiSteps.setDriver()"}}],"line":20,"name":"","description":"","id":"pagination-validation;","after":[{"result":{"duration":601000000,"status":"passed"},"match":{"location":"steps.Hooks.tearDown(io.cucumber.java.Scenario)"}}],"type":"scenario","keyword":"Scenario","steps":[{"result":{"status":"skipped"},"line":21,"name":"the user should see “Tokyo” City with the info below and an image","match":{},"rows":[{"cells":["City: Tokyo"]},{"cells":["Country: Japan"]},{"cells":["Population: 37,435,191"]}],"keyword":"Then "},{"result":{"status":"skipped"},"line":26,"name":"the user clicks on the “Next” button","match":{},"keyword":"When "},{"result":{"status":"skipped"},"line":27,"name":"the user should see “Delhi” City with the info below and an image","match":{},"rows":[{"cells":["City: Delhi"]},{"cells":["Country: India"]},{"cells":["Population: 29,399,141"]}],"keyword":"Then "},{"result":{"status":"skipped"},"line":32,"name":"the user clicks on the “Next” button","match":{},"keyword":"When "},{"result":{"status":"skipped"},"line":33,"name":"the user should see “Shangai“ City with the info below and an image","match":{},"rows":[{"cells":["City: Shangai"]},{"cells":["Country: China"]},{"cells":["Population: 26,317,104"]}],"keyword":"Then "},{"result":{"status":"skipped"},"line":38,"name":"the user clicks on the “Next” button","match":{},"keyword":"When "},{"result":{"status":"skipped"},"line":39,"name":"the user should see “Sao Paulo“ City with the info below and an image","match":{},"rows":[{"cells":["City: Sao Paulo"]},{"cells":["Country: Brasil"]},{"cells":["Population: 21,846,507"]}],"keyword":"Then "},{"result":{"status":"skipped"},"line":44,"name":"the user clicks on the “Next” button","match":{},"keyword":"When "},{"result":{"status":"skipped"},"line":45,"name":"the user should see “Mexico City” City with the info below and an image","match":{},"rows":[{"cells":["City: Mexico City"]},{"cells":["Country: Mexico"]},{"cells":["Population: 21,671,908"]}],"keyword":"Then "}],"tags":[{"name":"@Project5"}]}],"name":"pagination validation","description":"","id":"pagination-validation","keyword":"Feature","uri":"file:src/test/resources/features/Project05.feature","tags":[{"name":"@Project5","type":"Tag","location":{"line":1,"column":1}}]}]